{
  "scenarioPath": "C:\\Users\\37814\\Desktop\\tianming\\scenarios\\天启七年·九月（官方）.json",
  "backupPath": "C:\\Users\\37814\\Desktop\\tianming\\scenarios\\天启七年·九月（官方）.json.pre-historical-supplement-20260517-204716.bak",
  "supplementPath": "C:\\Users\\37814\\Desktop\\tianming\\web\\data\\scenario-supplements\\tianqi7-ming2-historical-supplement.json",
  "addedFactions": [
    "土默特蒙古",
    "叶尔羌汗国",
    "吐鲁番诸伯克",
    "哈萨克汗国",
    "瓦刺诸部",
    "野人女真诸部",
    "虾夷地与松前氏",
    "日本幕府",
    "大越黎郑阮格局",
    "喀尔喀蒙古"
  ],
  "addedAdminDivisions": [
    "朵甘思宣慰司",
    "鞑靼土默特部",
    "叶尔羌",
    "吐鲁番",
    "哈萨克",
    "北哈萨克",
    "东哈萨克",
    "瓦刺",
    "苦兀（野人女真）",
    "北山女真",
    "北海道",
    "本州",
    "九州",
    "四国",
    "交趾",
    "漠南诸部",
    "喀尔喀蒙古"
  ],
  "movedAdminDivisions": [],
  "addedCharacters": [
    "卜失兔汗",
    "阿布达勒拉提甫汗",
    "吐鲁番伯克",
    "也昔木汗",
    "拜巴噶斯台吉",
    "黑龙江部酋",
    "松前公广",
    "虾夷诸酋",
    "德川家光",
    "德川秀忠",
    "黎神宗",
    "郑梉",
    "阮福源",
    "却图汗",
    "土谢图汗衮布"
  ],
  "addedFamilies": [
    "博尔济吉特·土默特",
    "察合台后裔·叶尔羌",
    "吐鲁番伯克诸家",
    "成吉思汗系·哈萨克",
    "和硕特部",
    "黑龙江诸部",
    "松前氏",
    "阿伊努诸部",
    "德川氏",
    "后黎皇室",
    "郑氏·东京",
    "阮氏·广南",
    "喀尔喀诸汗",
    "土谢图汗部"
  ],
  "addedFactionRelations": [
    "土默特蒙古->明朝廷",
    "土默特蒙古->察哈尔",
    "土默特蒙古->后金",
    "土默特蒙古->科尔沁蒙古",
    "叶尔羌汗国->吐鲁番诸伯克",
    "叶尔羌汗国->哈萨克汗国",
    "叶尔羌汗国->瓦刺诸部",
    "叶尔羌汗国->明朝廷",
    "吐鲁番诸伯克->叶尔羌汗国",
    "吐鲁番诸伯克->瓦刺诸部",
    "吐鲁番诸伯克->哈萨克汗国",
    "哈萨克汗国->叶尔羌汗国",
    "哈萨克汗国->瓦刺诸部",
    "哈萨克汗国->吐鲁番诸伯克",
    "瓦刺诸部->哈萨克汗国",
    "瓦刺诸部->叶尔羌汗国",
    "瓦刺诸部->喀尔喀蒙古",
    "野人女真诸部->后金",
    "野人女真诸部->明朝廷",
    "野人女真诸部->朝鲜",
    "虾夷地与松前氏->日本幕府",
    "虾夷地与松前氏->后金",
    "日本幕府->明朝廷",
    "日本幕府->葡萄牙·澳门",
    "日本幕府->荷兰·台海(东印度公司)",
    "日本幕府->朝鲜",
    "大越黎郑阮格局->明朝廷",
    "大越黎郑阮格局->西班牙·马尼拉",
    "大越黎郑阮格局->葡萄牙·澳门",
    "喀尔喀蒙古->察哈尔",
    "喀尔喀蒙古->瓦刺诸部",
    "喀尔喀蒙古->后金"
  ],
  "addedRelations": [
    "德川家光->德川秀忠",
    "黎神宗->郑梉",
    "郑梉->阮福源",
    "卜失兔汗->林丹汗",
    "阿布达勒拉提甫汗->吐鲁番伯克"
  ],
  "fieldAudit": {
    "originalFactionKeyCount": 68,
    "originalCharacterCommonKeyCount": 54,
    "supplementFactionMissing": {
      "土默特蒙古": [],
      "叶尔羌汗国": [],
      "吐鲁番诸伯克": [],
      "哈萨克汗国": [],
      "瓦刺诸部": [],
      "野人女真诸部": [],
      "虾夷地与松前氏": [],
      "日本幕府": [],
      "大越黎郑阮格局": [],
      "喀尔喀蒙古": []
    },
    "supplementCharacterMissing": {
      "卜失兔汗": [],
      "阿布达勒拉提甫汗": [],
      "吐鲁番伯克": [],
      "也昔木汗": [],
      "拜巴噶斯台吉": [],
      "黑龙江部酋": [],
      "松前公广": [],
      "虾夷诸酋": [],
      "德川家光": [],
      "德川秀忠": [],
      "黎神宗": [],
      "郑梉": [],
      "阮福源": [],
      "却图汗": [],
      "土谢图汗衮布": []
    }
  }
}
